textual_countdown/__init__.py
textual_countdown/__main__.py
textual_countdown/countdown.py
textual_countdown/py.typed
textual_countdown-1.0.0.dist-info/WHEEL
textual_countdown-1.0.0.dist-info/METADATA
textual_countdown-1.0.0.dist-info/RECORD
