Metadata-Version: 2.4
Name: textual-countdown
Version: 1.0.0
Summary: A visual countdown widget for Textual applications
Keywords: terminal,library,widget
Author: Dave Pearson
Author-email: Dave Pearson <davep@davep.org>
License-Expression: MIT
Classifier: Environment :: Console
Classifier: Development Status :: 5 - Production/Stable
Classifier: Intended Audience :: Developers
Classifier: Operating System :: OS Independent
Classifier: Programming Language :: Python :: 3.9
Classifier: Programming Language :: Python :: 3.10
Classifier: Programming Language :: Python :: 3.11
Classifier: Programming Language :: Python :: 3.12
Classifier: Programming Language :: Python :: 3.13
Classifier: Programming Language :: Python :: 3.14
Classifier: Topic :: Terminals
Classifier: Topic :: Software Development :: Libraries
Classifier: Typing :: Typed
Requires-Dist: textual>=1.0.0
Requires-Python: >=3.9
Project-URL: Discussions, https://github.com/davep/textual-countdown/discussions
Project-URL: Documentation, https://textual-countdown.davep.dev
Project-URL: Homepage, https://textual-countdown.davep.dev
Project-URL: Issues, https://github.com/davep/textual-countdown/issues
Project-URL: Repository, https://github.com/davep/textual-countdown
Project-URL: Source, https://github.com/davep/textual-countdown
